algobrew/__init__.py
algobrew/myfunctions.py
algobrew-0.1.1.dist-info/LICENSE
algobrew-0.1.1.dist-info/METADATA
algobrew-0.1.1.dist-info/WHEEL
algobrew-0.1.1.dist-info/top_level.txt
algobrew-0.1.1.dist-info/RECORD
