Metadata-Version: 2.1
Name: algobrew
Version: 0.1.1
Summary: My first Python library
Home-page: UNKNOWN
Author: Me
License: MIT
Platform: UNKNOWN
License-File: LICENSE
